ln_jupyter_extra/__init__.py
ln_jupyter_extra/_version.py
ln_jupyter_extra/labextension/package.json
ln_jupyter_extra/labextension/schemas/ln-jupyter-extra/package.json.orig
ln_jupyter_extra/labextension/schemas/ln-jupyter-extra/plugin.json
ln_jupyter_extra/labextension/static/142.d03adb51917027ecc7aa.js
ln_jupyter_extra/labextension/static/142.d03adb51917027ecc7aa.js.LICENSE.txt
ln_jupyter_extra/labextension/static/353.7ee8c0b40876b6b36e29.js
ln_jupyter_extra/labextension/static/455.d839796f887c270c0e32.js
ln_jupyter_extra/labextension/static/581.9c8cb14efe1a0071f41c.js
ln_jupyter_extra/labextension/static/590.92be034ee79fe2495943.js
ln_jupyter_extra/labextension/static/64.404e9f3341a96cb14de7.js
ln_jupyter_extra/labextension/static/751.3cde7e9ae930f25a5854.js
ln_jupyter_extra/labextension/static/916.03abba849aaf8b550155.js
ln_jupyter_extra/labextension/static/916.03abba849aaf8b550155.js.LICENSE.txt
ln_jupyter_extra/labextension/static/remoteEntry.f182bedde2c7a2ea4ef2.js
ln_jupyter_extra/labextension/static/style.js
ln_jupyter_extra/labextension/static/third-party-licenses.json
ln_jupyter_extra-0.1.37.data/data/share/jupyter/labextensions/ln-jupyter-extra/package.json
ln_jupyter_extra-0.1.37.data/data/share/jupyter/labextensions/ln-jupyter-extra/schemas/ln-jupyter-extra/package.json.orig
ln_jupyter_extra-0.1.37.data/data/share/jupyter/labextensions/ln-jupyter-extra/schemas/ln-jupyter-extra/plugin.json
ln_jupyter_extra-0.1.37.data/data/share/jupyter/labextensions/ln-jupyter-extra/static/142.d03adb51917027ecc7aa.js
ln_jupyter_extra-0.1.37.data/data/share/jupyter/labextensions/ln-jupyter-extra/static/142.d03adb51917027ecc7aa.js.LICENSE.txt
ln_jupyter_extra-0.1.37.data/data/share/jupyter/labextensions/ln-jupyter-extra/static/353.7ee8c0b40876b6b36e29.js
ln_jupyter_extra-0.1.37.data/data/share/jupyter/labextensions/ln-jupyter-extra/static/455.d839796f887c270c0e32.js
ln_jupyter_extra-0.1.37.dist-info/METADATA
ln_jupyter_extra-0.1.37.dist-info/WHEEL
ln_jupyter_extra-0.1.37.dist-info/licenses/LICENSE
ln_jupyter_extra-0.1.37.dist-info/RECORD
